<ArGpsLocationData><Entry><id>0</id><lat>35.88735231187813</lat><lng>128.61277696976828</lng><altitude>0</altitude><altitudeMode>GroundRelative</altitudeMode><name>Logo1</name><meshId>Logo</meshId><movementSmoothing>0.05</movementSmoothing><maxNumberOfLocationUpdates>0</maxNumberOfLocationUpdates><useMovingAverage>false</useMovingAverage><hideObjectUtilItIsPlaced>true</hideObjectUtilItIsPlaced></Entry><Entry><id>1</id><lat>35.88735231187813</lat><lng>128.6128745176673</lng><altitude>0</altitude><altitudeMode>GroundRelative</altitudeMode><name>Logo2</name><meshId>logo</meshId><movementSmoothing>0.05</movementSmoothing><maxNumberOfLocationUpdates>0</maxNumberOfLocationUpdates><useMovingAverage>false</useMovingAverage><hideObjectUtilItIsPlaced>true</hideObjectUtilItIsPlaced></Entry><Entry><id>2</id><lat>35.887358763346086</lat><lng>128.61294419473768</lng><altitude>0</altitude><altitudeMode>GroundRelative</altitudeMode><name>Logo3</name><meshId>Logo</meshId><movementSmoothing>0.05</movementSmoothing><maxNumberOfLocationUpdates>0</maxNumberOfLocationUpdates><useMovingAverage>false</useMovingAverage><hideObjectUtilItIsPlaced>true</hideObjectUtilItIsPlaced></Entry><Entry><id>3</id><lat>35.887355537612194</lat><lng>128.61267145877542</lng><altitude>0</altitude><altitudeMode>GroundRelative</altitudeMode><name>Logo4</name><meshId>Logo</meshId><movementSmoothing>0.05</movementSmoothing><maxNumberOfLocationUpdates>0</maxNumberOfLocationUpdates><useMovingAverage>false</useMovingAverage><hideObjectUtilItIsPlaced>true</hideObjectUtilItIsPlaced></Entry><Entry><id>4</id><lat>35.88758133866601</lat><lng>128.61276303435392</lng><altitude>0</altitude><altitudeMode>GroundRelative</altitudeMode><name>Logo5</name><meshId>Logo</meshId><movementSmoothing>0.05</movementSmoothing><maxNumberOfLocationUpdates>0</maxNumberOfLocationUpdates><useMovingAverage>false</useMovingAverage><hideObjectUtilItIsPlaced>true</hideObjectUtilItIsPlaced></Entry><Entry><id>6</id><lat>35.88850260164763</lat><lng>128.61224687282248</lng><altitude>0</altitude><altitudeMode>GroundRelative</altitudeMode><name>Lake01</name><meshId>Lake</meshId><movementSmoothing>0.05</movementSmoothing><maxNumberOfLocationUpdates>0</maxNumberOfLocationUpdates><useMovingAverage>false</useMovingAverage><hideObjectUtilItIsPlaced>true</hideObjectUtilItIsPlaced></Entry><Entry><id>7</id><lat>35.88847126240435</lat><lng>128.61203411737648</lng><altitude>0</altitude><altitudeMode>GroundRelative</altitudeMode><name>Lake02</name><meshId>Lake</meshId><movementSmoothing>0.05</movementSmoothing><maxNumberOfLocationUpdates>0</maxNumberOfLocationUpdates><useMovingAverage>false</useMovingAverage><hideObjectUtilItIsPlaced>true</hideObjectUtilItIsPlaced></Entry><Entry><id>8</id><lat>35.88873294470142</lat><lng>128.61192580551295</lng><altitude>0</altitude><altitudeMode>GroundRelative</altitudeMode><name>Lake03</name><meshId>Lake</meshId><movementSmoothing>0.05</movementSmoothing><maxNumberOfLocationUpdates>0</maxNumberOfLocationUpdates><useMovingAverage>false</useMovingAverage><hideObjectUtilItIsPlaced>true</hideObjectUtilItIsPlaced></Entry></ArGpsLocationData>